board/__init__.py
board/controller.py
board/main.py
board/model.py
board/static/main.js
board/static/spritesheet.svg
board/static/vertical-logo.svg
board/templates/base.html
board/templates/index.html
board/templates/welcome.html
qool_board-1.0.0.dist-info/LICENSE
qool_board-1.0.0.dist-info/METADATA
qool_board-1.0.0.dist-info/WHEEL
qool_board-1.0.0.dist-info/top_level.txt
qool_board-1.0.0.dist-info/RECORD
