Metadata-Version: 2.1
Name: qool-board
Version: 1.0.0
Summary: UNKNOWN
Home-page: UNKNOWN
Author: UNKNOWN
Author-email: UNKNOWN
License: UNKNOWN
Platform: UNKNOWN
Requires-Dist: mitama
Requires-Dist: pytz
Requires-Dist: python-dateutil
